application/docker_manager.py
application/main.py
application/messages.py
application/styles.tcss
application/util/config.py
application/util/helper.py
application/widget/containers.py
application/widget/content.py
application/widget/help.py
application/widget/images.py
application/widget/log_viewer.py
application/widget/settings.py
application/widget/shell.py
application/widget/startup_error_modal.py
application/widget/statistics.py
application/widget/terminal.py
application/widget/topbar.py
pocker_tui-1.18.4.dist-info/LICENSE
pocker_tui-1.18.4.dist-info/METADATA
pocker_tui-1.18.4.dist-info/WHEEL
pocker_tui-1.18.4.dist-info/entry_points.txt
pocker_tui-1.18.4.dist-info/RECORD
