Metadata-Version: 2.3
Name: pocker-tui
Version: 1.18.4
Summary: CLI tool for docker images, containers, logs and more.
Author: pommee
Requires-Python: >=3.10.9,<4.0.0
Classifier: Programming Language :: Python :: 3
Classifier: Programming Language :: Python :: 3.11
Classifier: Programming Language :: Python :: 3.12
Classifier: Programming Language :: Python :: 3.13
Requires-Dist: click (>=8.1.7,<9.0.0)
Requires-Dist: colorama (>=0.4.6,<0.5.0)
Requires-Dist: docker (>=7.0.0,<8.0.0)
Requires-Dist: packaging (>=24.1,<25.0)
Requires-Dist: pydantic (>=2.7.3,<3.0.0)
Requires-Dist: pyte (>=0.8.2,<0.9.0)
Requires-Dist: pywinpty (>=2.0.13,<3.0.0) ; sys_platform == "win32"
Requires-Dist: pyyaml (>=6.0.1,<7.0.0)
Requires-Dist: textual (>=1.0.0,<2.0.0)
Requires-Dist: textual-plotext (>=1.0.0,<2.0.0)
Requires-Dist: yaspin (>=3.0.2,<4.0.0)
Project-URL: Documentation, https://github.com/pommee/Pocker/blob/main/README.md
Project-URL: Funding, https://buymeacoffee.com/pommee
Project-URL: Homepage, https://github.com/pommee/Pocker
Project-URL: Repository, https://github.com/pommee/Pocker
Project-URL: Release notes, https://github.com/pommee/Pocker/blob/main/CHANGELOG.md
